edx_enterprise_subsidy_client/__init__.py
edx_enterprise_subsidy_client/client.py
edx_enterprise_subsidy_client-2.0.18.dist-info/licenses/LICENSE
edx_enterprise_subsidy_client-2.0.18.dist-info/licenses/LICENSE.txt
edx_enterprise_subsidy_client-2.0.18.dist-info/METADATA
edx_enterprise_subsidy_client-2.0.18.dist-info/WHEEL
edx_enterprise_subsidy_client-2.0.18.dist-info/top_level.txt
edx_enterprise_subsidy_client-2.0.18.dist-info/RECORD
